environment_variables/__init__.py
environment_variables/read/__init__.py
environment_variables/read/read_env.py
environment_variables/read/read_json.py
environment_variables_python-0.0.1.dist-info/LICENSE
environment_variables_python-0.0.1.dist-info/WHEEL
environment_variables_python-0.0.1.dist-info/METADATA
environment_variables_python-0.0.1.dist-info/RECORD
