Metadata-Version: 2.1
Name: environment-variables-python
Version: 0.0.1
Summary: this is not a awesome description
Home-page: https://github.com/jorgepvasconcelos/environment-variables-python
License: MIT
Keywords: environment,env
Author: Jorge Vasconcelos
Author-email: john@example.com
Requires-Python: >=3.9,<4.0
Classifier: License :: OSI Approved :: MIT License
Classifier: Programming Language :: Python :: 3
Classifier: Programming Language :: Python :: 3.10
Classifier: Programming Language :: Python :: 3.9
Requires-Dist: python-dotenv (>=0.20.0,<0.21.0)
Project-URL: Repository, https://github.com/jorgepvasconcelos/environment-variables-python
